{
  "bucket": "Active_TOP|GIRLS",
  "department": "Active",
  "garment_type": "TOP",
  "gender": "GIRLS",
  "n": 13,
  "size_range": [
    "XS",
    "S",
    "M",
    "L",
    "XL",
    "XXL"
  ],
  "measurement_rules": {
    "must": {
      "B34": {
        "rate": 0.769,
        "count": 10
      },
      "D13": {
        "rate": 0.846,
        "count": 11,
        "tolerance": {
          "standard": 0.25,
          "display": "1/4",
          "dominance_pct": 100.0,
          "n": 11
        }
      },
      "B29": {
        "rate": 0.923,
        "count": 12,
        "tolerance": {
          "standard": 0.125,
          "display": "1/8",
          "dominance_pct": 100.0,
          "n": 11
        }
      },
      "C3": {
        "rate": 0.769,
        "count": 10,
        "tolerance": {
          "standard": 0.125,
          "display": "1/8",
          "dominance_pct": 100.0,
          "n": 10
        }
      },
      "B26": {
        "rate": 0.923,
        "count": 12,
        "tolerance": {
          "standard": 0.125,
          "display": "1/8",
          "dominance_pct": 100.0,
          "n": 12
        }
      },
      "J10": {
        "rate": 0.846,
        "count": 11,
        "tolerance": {
          "standard": 0.5,
          "display": "1/2",
          "dominance_pct": 80.0,
          "n": 10
        },
        "tier1_enforced": true
      },
      "I5": {
        "rate": 0.923,
        "count": 12,
        "tolerance": {
          "standard": 0.5,
          "display": "1/2",
          "dominance_pct": 100.0,
          "n": 12
        },
        "tier1_enforced": true
      },
      "J9": {
        "rate": 0.923,
        "count": 12,
        "tolerance": {
          "standard": 0.5,
          "display": "1/2",
          "dominance_pct": 100.0,
          "n": 12
        },
        "tier1_enforced": true
      },
      "B25": {
        "rate": 1.0,
        "count": 13,
        "tolerance": {
          "standard": 0.25,
          "display": "1/4",
          "dominance_pct": 100.0,
          "n": 13
        }
      },
      "E13": {
        "rate": 0.769,
        "count": 10,
        "tolerance": {
          "standard": 0.125,
          "display": "1/8",
          "dominance_pct": 70.0,
          "n": 10
        }
      },
      "F10": {
        "rate": 0.538,
        "count": 7,
        "tolerance": {
          "standard": 0.5,
          "display": "1/2",
          "dominance_pct": 100.0,
          "n": 7
        },
        "tier1_enforced": true
      },
      "C1": {
        "rate": 0.615,
        "count": 8,
        "tolerance": {
          "standard": 0.5,
          "display": "1/2",
          "dominance_pct": 62.5,
          "n": 8
        },
        "tier1_enforced": true
      },
      "E1": {
        "rate": 0.538,
        "count": 7,
        "tolerance": {
          "standard": 0.5,
          "display": "1/2",
          "dominance_pct": 57.1,
          "n": 7
        },
        "tier1_enforced": true
      }
    },
    "recommend": {
      "T10": {
        "rate": 0.615,
        "count": 8
      },
      "C7": {
        "rate": 0.538,
        "count": 7,
        "tolerance": {
          "standard": 0.125,
          "display": "1/8",
          "dominance_pct": 100.0,
          "n": 7
        }
      }
    },
    "optional": {
      "F11": {
        "rate": 0.462,
        "count": 6,
        "tolerance": {
          "standard": 0.5,
          "display": "1/2",
          "dominance_pct": 100.0,
          "n": 6
        }
      },
      "C2": {
        "rate": 0.308,
        "count": 4,
        "tolerance": {
          "standard": 0.125,
          "display": "1/8",
          "dominance_pct": 75.0,
          "n": 4
        }
      },
      "Z18": {
        "rate": 0.462,
        "count": 6
      },
      "E9": {
        "rate": 0.462,
        "count": 6,
        "tolerance": {
          "standard": 0.25,
          "display": "1/4",
          "dominance_pct": 100.0,
          "n": 6
        }
      }
    }
  },
  "median_values": {
    "F11": {
      "size_medians": {
        "XS": 14.062,
        "S": 15.062,
        "M": 16.062,
        "L": 17.188,
        "XL": 18.312,
        "XXL": 19.438
      }
    },
    "F9": {
      "size_medians": {
        "XS": 2.875,
        "S": 3.5,
        "M": 4.125,
        "L": 4.75,
        "XL": 5.375,
        "XXL": 6.0
      }
    },
    "B34": {
      "size_medians": {
        "XS": 21.0,
        "S": 22.0,
        "M": 22.0,
        "L": 23.0,
        "XL": 23.0,
        "XXL": 23.0
      }
    },
    "D13": {
      "size_medians": {
        "XS": 5.25,
        "S": 5.75,
        "M": 6.25,
        "L": 6.375,
        "XL": 6.75,
        "XXL": 7.125
      }
    },
    "C2": {
      "size_medians": {
        "XS": 1.0,
        "S": 1.0,
        "M": 1.0,
        "L": 1.0,
        "XL": 1.0,
        "XXL": 1.0
      }
    },
    "F59": {
      "size_medians": {
        "XS": 8.0,
        "S": 8.625,
        "M": 9.25,
        "L": 10.125,
        "XL": 11.0,
        "XXL": 11.375
      }
    },
    "B29": {
      "size_medians": {
        "XS": 1.0,
        "S": 1.0,
        "M": 1.0,
        "L": 1.125,
        "XL": 1.25,
        "XXL": 1.375
      }
    },
    "F8": {
      "size_medians": {
        "XS": 2.75,
        "S": 3.125,
        "M": 3.5,
        "L": 3.875,
        "XL": 4.25,
        "XXL": 4.625
      }
    },
    "C3": {
      "size_medians": {
        "XS": 1.125,
        "S": 0.875,
        "M": 1.375,
        "L": 1.031,
        "XL": 1.25,
        "XXL": 1.375
      }
    },
    "B26": {
      "size_medians": {
        "XS": 2.5,
        "S": 3.0,
        "M": 3.125,
        "L": 3.25,
        "XL": 3.375,
        "XXL": 3.688
      }
    },
    "F61": {
      "size_medians": {
        "M": 3.0,
        "L": 3.438,
        "XL": 3.875
      }
    },
    "J10": {
      "size_medians": {
        "XS": 13.375,
        "S": 14.5,
        "M": 15.625,
        "L": 16.875,
        "XL": 18.5,
        "XXL": 19.0
      }
    },
    "I5": {
      "size_medians": {
        "XS": 12.688,
        "S": 13.688,
        "M": 14.688,
        "L": 15.812,
        "XL": 16.938,
        "XXL": 18.062
      }
    },
    "T10": {
      "size_medians": {
        "XS": 0.5,
        "S": 0.5,
        "M": 0.5,
        "L": 0.5,
        "XL": 0.5,
        "XXL": 0.5
      }
    },
    "F6": {
      "size_medians": {
        "XS": 7.25,
        "S": 7.875,
        "M": 8.25,
        "L": 8.75,
        "XL": 9.25,
        "XXL": 9.75
      }
    },
    "J9": {
      "size_medians": {
        "XS": 13.375,
        "S": 14.5,
        "M": 15.625,
        "L": 17.062,
        "XL": 18.625,
        "XXL": 19.25
      }
    },
    "F4": {
      "size_medians": {
        "XS": 2.875,
        "S": 3.125,
        "M": 3.5,
        "L": 3.812,
        "XL": 4.25,
        "XXL": 4.438
      }
    },
    "B25": {
      "size_medians": {
        "XS": 6.5,
        "S": 6.75,
        "M": 7.0,
        "L": 7.25,
        "XL": 7.5,
        "XXL": 7.75
      }
    },
    "F62": {
      "size_medians": {
        "XS": 9.25,
        "S": 10.25,
        "M": 11.25,
        "L": 12.375,
        "XL": 13.5,
        "XXL": 14.625
      }
    },
    "F10": {
      "size_medians": {
        "XS": 12.0,
        "S": 13.0,
        "M": 14.0,
        "L": 15.125,
        "XL": 16.25,
        "XXL": 17.375
      }
    },
    "C7": {
      "size_medians": {
        "XS": 0.5,
        "S": 0.5,
        "M": 0.5,
        "L": 0.5,
        "XL": 0.5,
        "XXL": 0.5
      }
    },
    "Z21": {
      "size_medians": {
        "XS": 2.0,
        "S": 2.0,
        "M": 2.0,
        "L": 2.0,
        "XL": 2.0,
        "XXL": 2.0
      }
    },
    "E13": {
      "size_medians": {
        "XS": 2.812,
        "S": 4.75,
        "M": 3.312,
        "L": 3.5,
        "XL": 3.812,
        "XXL": 5.75
      }
    },
    "E1": {
      "size_medians": {
        "XS": 13.5,
        "S": 14.125,
        "M": 14.75,
        "L": 15.375,
        "XL": 16.0,
        "XXL": 16.375
      }
    },
    "C1": {
      "size_medians": {
        "XS": 13.5,
        "S": 14.375,
        "M": 15.312,
        "L": 16.438,
        "XL": 17.562,
        "XXL": 18.688
      }
    },
    "Z18": {
      "size_medians": {
        "XS": 0.5,
        "S": 0.5,
        "M": 0.5,
        "L": 0.5,
        "XL": 0.5,
        "XXL": 0.5
      }
    },
    "E28": {
      "size_medians": {
        "XS": 1.0,
        "S": 1.0,
        "M": 1.0,
        "L": 1.0,
        "XL": 1.0,
        "XXL": 1.0
      }
    },
    "E9": {
      "size_medians": {
        "XS": 4.25,
        "S": 4.5,
        "M": 4.75,
        "L": 5.125,
        "XL": 5.375,
        "XXL": 5.875
      }
    },
    "E27": {
      "size_medians": {
        "XS": 1.75,
        "S": 1.75,
        "M": 1.75,
        "L": 1.75,
        "XL": 1.75,
        "XXL": 1.75
      }
    },
    "D19": {
      "size_medians": {
        "XS": 10.375,
        "S": 11.0,
        "M": 11.625,
        "L": 12.375,
        "XL": 13.125,
        "XXL": 13.875
      }
    },
    "I11": {
      "size_medians": {
        "XS": 1.438,
        "S": 1.438,
        "M": 1.438,
        "L": 1.438,
        "XL": 1.438,
        "XXL": 1.438
      }
    },
    "E6": {
      "size_medians": {
        "XS": 21.25,
        "S": 23.25,
        "M": 25.25,
        "L": 27.25,
        "XL": 29.25,
        "XXL": 29.75
      }
    },
    "C4": {
      "size_medians": {
        "XL": 1.938,
        "XXL": 2.062
      }
    },
    "K25": {
      "size_medians": {
        "XS": 0.875,
        "S": 0.875,
        "M": 0.875,
        "L": 0.875,
        "XL": 0.875,
        "XXL": 0.875
      }
    },
    "B1": {
      "size_medians": {
        "XS": 7.5,
        "S": 7.625,
        "M": 7.75,
        "L": 8.188,
        "XL": 8.625,
        "XXL": 9.062
      }
    },
    "D20": {
      "size_medians": {
        "XXL": 2.188
      }
    },
    "K23": {
      "size_medians": {
        "XS": 6.875,
        "S": 7.062,
        "M": 7.5,
        "L": 7.625,
        "XL": 7.75,
        "XXL": 7.875
      }
    },
    "Z5": {
      "size_medians": {
        "XS": 3.375,
        "S": 3.438,
        "M": 3.5,
        "XL": 3.625
      }
    },
    "I2": {
      "size_medians": {
        "XS": 15.625,
        "S": 16.625,
        "M": 17.625,
        "L": 18.75,
        "XL": 19.875,
        "XXL": 21.0
      }
    },
    "N16": {
      "size_medians": {
        "S": 2.25,
        "M": 2.25,
        "L": 2.25,
        "XL": 2.25,
        "XXL": 2.25
      }
    },
    "E12": {
      "size_medians": {
        "S": 5.938,
        "M": 6.188,
        "L": 6.438,
        "XXL": 6.938
      }
    },
    "E25": {
      "size_medians": {
        "XS": 2.625,
        "S": 2.625,
        "M": 2.625,
        "L": 2.625,
        "XL": 2.625,
        "XXL": 2.625
      }
    }
  },
  "grading_rules": {
    "F11": {
      "typical_increment": 1.125,
      "n_pairs": 30
    },
    "C8": {
      "typical_increment": 0.0,
      "n_pairs": 5
    },
    "F9": {
      "typical_increment": 0.25,
      "n_pairs": 15
    },
    "B34": {
      "typical_increment": 0.0,
      "n_pairs": 50
    },
    "D13": {
      "typical_increment": 0.375,
      "n_pairs": 51
    },
    "C2": {
      "typical_increment": 0.0,
      "n_pairs": 20
    },
    "F59": {
      "typical_increment": 0.625,
      "n_pairs": 10
    },
    "B29": {
      "typical_increment": 0.125,
      "n_pairs": 44
    },
    "T11": {
      "typical_increment": 0.0,
      "n_pairs": 5
    },
    "F8": {
      "typical_increment": 0.375,
      "n_pairs": 12
    },
    "C3": {
      "typical_increment": 0.125,
      "n_pairs": 43
    },
    "B26": {
      "typical_increment": 0.25,
      "n_pairs": 47
    },
    "F61": {
      "typical_increment": 0.375,
      "n_pairs": 7
    },
    "J10": {
      "typical_increment": 1.125,
      "n_pairs": 54
    },
    "I5": {
      "typical_increment": 1.125,
      "n_pairs": 60
    },
    "T10": {
      "typical_increment": 0.0,
      "n_pairs": 40
    },
    "F6": {
      "typical_increment": 0.5,
      "n_pairs": 15
    },
    "J9": {
      "typical_increment": 1.125,
      "n_pairs": 60
    },
    "F4": {
      "typical_increment": 0.375,
      "n_pairs": 12
    },
    "B25": {
      "typical_increment": 0.25,
      "n_pairs": 63
    },
    "F62": {
      "typical_increment": 1.125,
      "n_pairs": 10
    },
    "F10": {
      "typical_increment": 1.125,
      "n_pairs": 35
    },
    "C7": {
      "typical_increment": 0.0,
      "n_pairs": 34
    },
    "Z21": {
      "typical_increment": 0.0,
      "n_pairs": 10
    },
    "E13": {
      "typical_increment": 0.25,
      "n_pairs": 43
    },
    "I9": {
      "typical_increment": 0.0,
      "n_pairs": 5
    },
    "E1": {
      "typical_increment": 2.0,
      "n_pairs": 35
    },
    "C1": {
      "typical_increment": 1.0,
      "n_pairs": 40
    },
    "G7": {
      "typical_increment": 0.5,
      "n_pairs": 5
    },
    "Z18": {
      "typical_increment": 0.0,
      "n_pairs": 30
    },
    "G2": {
      "typical_increment": 0.5,
      "n_pairs": 5
    },
    "E28": {
      "typical_increment": 0.0,
      "n_pairs": 14
    },
    "E9": {
      "typical_increment": 0.375,
      "n_pairs": 27
    },
    "E27": {
      "typical_increment": 0.0,
      "n_pairs": 14
    },
    "D19": {
      "typical_increment": 0.75,
      "n_pairs": 10
    },
    "I11": {
      "typical_increment": 0.0,
      "n_pairs": 10
    },
    "E6": {
      "typical_increment": 2.0,
      "n_pairs": 10
    },
    "C4": {
      "typical_increment": 0.125,
      "n_pairs": 6
    },
    "B2": {
      "typical_increment": 0.0,
      "n_pairs": 5
    },
    "K25": {
      "typical_increment": 0.0,
      "n_pairs": 10
    },
    "B1": {
      "typical_increment": 0.375,
      "n_pairs": 10
    },
    "D20": {
      "typical_increment": 0.125,
      "n_pairs": 5
    },
    "K23": {
      "typical_increment": 0.25,
      "n_pairs": 10
    },
    "D21": {
      "typical_increment": 0.125,
      "n_pairs": 5
    },
    "W34": {
      "typical_increment": 0.125,
      "n_pairs": 5
    },
    "Z26": {
      "typical_increment": 0.125,
      "n_pairs": 9
    },
    "C6": {
      "typical_increment": 0.0,
      "n_pairs": 5
    },
    "Z5": {
      "typical_increment": 0.0,
      "n_pairs": 8
    },
    "R1": {
      "typical_increment": 0.0,
      "n_pairs": 5
    },
    "P26": {
      "typical_increment": 0.25,
      "n_pairs": 5
    },
    "I2": {
      "typical_increment": 1.125,
      "n_pairs": 10
    },
    "E15": {
      "typical_increment": 0.25,
      "n_pairs": 5
    },
    "N16": {
      "typical_increment": 0.0,
      "n_pairs": 9
    },
    "P71": {
      "typical_increment": 0.125,
      "n_pairs": 1
    },
    "E12": {
      "typical_increment": 0.25,
      "n_pairs": 8
    },
    "E25": {
      "typical_increment": 0.0,
      "n_pairs": 10
    },
    "S21": {
      "typical_increment": 0.125,
      "n_pairs": 4
    },
    "J8": {
      "typical_increment": 0.375,
      "n_pairs": 5
    },
    "E2": {
      "typical_increment": 0.0,
      "n_pairs": 5
    },
    "E14": {
      "typical_increment": 0.25,
      "n_pairs": 5
    }
  },
  "tolerance_standards": {
    "F11": {
      "standard": 0.5,
      "display": "1/2",
      "dominance_pct": 100.0,
      "n": 6
    },
    "C8": {
      "standard": 0.125,
      "display": "1/8",
      "dominance_pct": 100.0,
      "n": 1
    },
    "F9": {
      "standard": 0.25,
      "display": "1/4",
      "dominance_pct": 100.0,
      "n": 3
    },
    "D13": {
      "standard": 0.25,
      "display": "1/4",
      "dominance_pct": 100.0,
      "n": 11
    },
    "C2": {
      "standard": 0.125,
      "display": "1/8",
      "dominance_pct": 75.0,
      "n": 4
    },
    "F59": {
      "standard": 0.25,
      "display": "1/4",
      "dominance_pct": 100.0,
      "n": 2
    },
    "B29": {
      "standard": 0.125,
      "display": "1/8",
      "dominance_pct": 100.0,
      "n": 11
    },
    "C3": {
      "standard": 0.125,
      "display": "1/8",
      "dominance_pct": 100.0,
      "n": 10
    },
    "B26": {
      "standard": 0.125,
      "display": "1/8",
      "dominance_pct": 100.0,
      "n": 12
    },
    "F61": {
      "standard": 0.125,
      "display": "1/8",
      "dominance_pct": 100.0,
      "n": 2
    },
    "J10": {
      "standard": 0.5,
      "display": "1/2",
      "dominance_pct": 80.0,
      "n": 10
    },
    "I5": {
      "standard": 0.5,
      "display": "1/2",
      "dominance_pct": 100.0,
      "n": 12
    },
    "F6": {
      "standard": 0.25,
      "display": "1/4",
      "dominance_pct": 100.0,
      "n": 3
    },
    "J9": {
      "standard": 0.5,
      "display": "1/2",
      "dominance_pct": 100.0,
      "n": 12
    },
    "B25": {
      "standard": 0.25,
      "display": "1/4",
      "dominance_pct": 100.0,
      "n": 13
    },
    "F62": {
      "standard": 0.25,
      "display": "1/4",
      "dominance_pct": 100.0,
      "n": 2
    },
    "F10": {
      "standard": 0.5,
      "display": "1/2",
      "dominance_pct": 100.0,
      "n": 7
    },
    "C7": {
      "standard": 0.125,
      "display": "1/8",
      "dominance_pct": 100.0,
      "n": 7
    },
    "Z21": {
      "standard": 0.125,
      "display": "1/8",
      "dominance_pct": 100.0,
      "n": 2
    },
    "E13": {
      "standard": 0.125,
      "display": "1/8",
      "dominance_pct": 70.0,
      "n": 10
    },
    "I9": {
      "standard": 0.125,
      "display": "1/8",
      "dominance_pct": 100.0,
      "n": 1
    },
    "E1": {
      "standard": 0.5,
      "display": "1/2",
      "dominance_pct": 57.1,
      "n": 7
    },
    "C1": {
      "standard": 0.5,
      "display": "1/2",
      "dominance_pct": 62.5,
      "n": 8
    },
    "G7": {
      "standard": 0.125,
      "display": "1/8",
      "dominance_pct": 100.0,
      "n": 1
    },
    "G2": {
      "standard": 0.125,
      "display": "1/8",
      "dominance_pct": 100.0,
      "n": 1
    },
    "E28": {
      "standard": 0.125,
      "display": "1/8",
      "dominance_pct": 100.0,
      "n": 3
    },
    "E9": {
      "standard": 0.25,
      "display": "1/4",
      "dominance_pct": 100.0,
      "n": 6
    },
    "E27": {
      "standard": 0.125,
      "display": "1/8",
      "dominance_pct": 100.0,
      "n": 3
    },
    "D19": {
      "standard": 0.25,
      "display": "1/4",
      "dominance_pct": 100.0,
      "n": 2
    },
    "I11": {
      "standard": 0.125,
      "display": "1/8",
      "dominance_pct": 100.0,
      "n": 2
    },
    "E6": {
      "standard": 0.5,
      "display": "1/2",
      "dominance_pct": 100.0,
      "n": 2
    },
    "C4": {
      "standard": 0.125,
      "display": "1/8",
      "dominance_pct": 100.0,
      "n": 2
    },
    "B2": {
      "standard": 0.125,
      "display": "1/8",
      "dominance_pct": 100.0,
      "n": 1
    },
    "K25": {
      "standard": 0.125,
      "display": "1/8",
      "dominance_pct": 100.0,
      "n": 2
    },
    "B1": {
      "standard": 0.25,
      "display": "1/4",
      "dominance_pct": 100.0,
      "n": 2
    },
    "D20": {
      "standard": 0.125,
      "display": "1/8",
      "dominance_pct": 100.0,
      "n": 2
    },
    "K23": {
      "standard": 0.25,
      "display": "1/4",
      "dominance_pct": 100.0,
      "n": 2
    },
    "D21": {
      "standard": 0.125,
      "display": "1/8",
      "dominance_pct": 100.0,
      "n": 1
    },
    "W34": {
      "standard": 0.125,
      "display": "1/8",
      "dominance_pct": 100.0,
      "n": 1
    },
    "Z26": {
      "standard": 0.125,
      "display": "1/8",
      "dominance_pct": 100.0,
      "n": 1
    },
    "C6": {
      "standard": 0.125,
      "display": "1/8",
      "dominance_pct": 100.0,
      "n": 1
    },
    "Z5": {
      "standard": 0.125,
      "display": "1/8",
      "dominance_pct": 100.0,
      "n": 2
    },
    "P26": {
      "standard": 0.125,
      "display": "1/8",
      "dominance_pct": 100.0,
      "n": 1
    },
    "I2": {
      "standard": 0.5,
      "display": "1/2",
      "dominance_pct": 100.0,
      "n": 2
    },
    "E15": {
      "standard": 0.125,
      "display": "1/8",
      "dominance_pct": 100.0,
      "n": 1
    },
    "N16": {
      "standard": 0.125,
      "display": "1/8",
      "dominance_pct": 100.0,
      "n": 2
    },
    "P71": {
      "standard": 0.125,
      "display": "1/8",
      "dominance_pct": 100.0,
      "n": 1
    },
    "E12": {
      "standard": 0.25,
      "display": "1/4",
      "dominance_pct": 100.0,
      "n": 2
    },
    "E25": {
      "standard": 0.125,
      "display": "1/8",
      "dominance_pct": 100.0,
      "n": 2
    },
    "S21": {
      "standard": 0.125,
      "display": "1/8",
      "dominance_pct": 100.0,
      "n": 1
    },
    "J8": {
      "standard": 0.25,
      "display": "1/4",
      "dominance_pct": 100.0,
      "n": 1
    },
    "E2": {
      "standard": 0.25,
      "display": "1/4",
      "dominance_pct": 100.0,
      "n": 1
    },
    "E14": {
      "standard": 0.125,
      "display": "1/8",
      "dominance_pct": 100.0,
      "n": 1
    }
  },
  "foundational_measurements": {
    "tier1_poms": [
      "F10",
      "C1",
      "J9",
      "J10",
      "E1",
      "I5"
    ],
    "enforced": true
  },
  "pom_sort_order": [
    "B25",
    "B1",
    "B26",
    "B29",
    "B34",
    "C1",
    "C3",
    "C7",
    "C2",
    "C4",
    "D20",
    "D13",
    "D19",
    "F4",
    "F8",
    "F6",
    "F9",
    "F10",
    "F11",
    "F59",
    "F61",
    "F62",
    "I5",
    "I2",
    "I11",
    "E1",
    "E9",
    "E12",
    "E13",
    "E6",
    "E27",
    "E28",
    "E25",
    "J9",
    "J10",
    "T10",
    "K23",
    "K25",
    "N16",
    "Z5",
    "Z18",
    "Z21"
  ]
}