{
  "bucket": "Sleepwear_SET|TODDLER",
  "department": "Sleepwear",
  "garment_type": "SET",
  "gender": "TODDLER",
  "n": 10,
  "size_range": [
    "2T",
    "3T",
    "4T",
    "5T"
  ],
  "measurement_rules": {
    "must": {
      "E1": {
        "rate": 0.7,
        "count": 7,
        "tolerance": {
          "standard": 0.375,
          "display": "3/8",
          "dominance_pct": 100.0,
          "n": 7
        },
        "tier1_enforced": true
      },
      "N3": {
        "rate": 0.8,
        "count": 8,
        "tolerance": {
          "standard": 0.25,
          "display": "1/4",
          "dominance_pct": 100.0,
          "n": 8
        }
      },
      "D13": {
        "rate": 0.9,
        "count": 9,
        "tolerance": {
          "standard": 0.25,
          "display": "1/4",
          "dominance_pct": 100.0,
          "n": 9
        }
      },
      "H1": {
        "rate": 1.0,
        "count": 10,
        "tier1_enforced": true
      },
      "B25": {
        "rate": 1.0,
        "count": 10,
        "tolerance": {
          "standard": 0.25,
          "display": "1/4",
          "dominance_pct": 100.0,
          "n": 10
        }
      },
      "H3": {
        "rate": 0.8,
        "count": 8,
        "tolerance": {
          "standard": 0.375,
          "display": "3/8",
          "dominance_pct": 100.0,
          "n": 8
        }
      },
      "K2": {
        "rate": 1.0,
        "count": 10,
        "tolerance": {
          "standard": 0.25,
          "display": "1/4",
          "dominance_pct": 100.0,
          "n": 10
        },
        "tier1_enforced": true
      },
      "O4": {
        "rate": 1.0,
        "count": 10,
        "tolerance": {
          "standard": 0.5,
          "display": "1/2",
          "dominance_pct": 80.0,
          "n": 10
        },
        "tier1_enforced": true
      },
      "E13": {
        "rate": 0.8,
        "count": 8,
        "tolerance": {
          "standard": 0.125,
          "display": "1/8",
          "dominance_pct": 87.5,
          "n": 8
        }
      },
      "N9": {
        "rate": 0.8,
        "count": 8,
        "tolerance": {
          "standard": 0.25,
          "display": "1/4",
          "dominance_pct": 100.0,
          "n": 8
        },
        "tier1_enforced": true
      },
      "B26": {
        "rate": 1.0,
        "count": 10,
        "tolerance": {
          "standard": 0.125,
          "display": "1/8",
          "dominance_pct": 100.0,
          "n": 10
        }
      },
      "K1": {
        "rate": 1.0,
        "count": 10,
        "tolerance": {
          "standard": 0.25,
          "display": "1/4",
          "dominance_pct": 100.0,
          "n": 10
        },
        "tier1_enforced": true
      },
      "H4": {
        "rate": 1.0,
        "count": 10,
        "tolerance": {
          "standard": 0.375,
          "display": "3/8",
          "dominance_pct": 100.0,
          "n": 10
        }
      },
      "C1": {
        "rate": 0.9,
        "count": 9,
        "tolerance": {
          "standard": 0.25,
          "display": "1/4",
          "dominance_pct": 100.0,
          "n": 9
        },
        "tier1_enforced": true
      },
      "B29": {
        "rate": 1.0,
        "count": 10,
        "tolerance": {
          "standard": 0.125,
          "display": "1/8",
          "dominance_pct": 100.0,
          "n": 10
        }
      },
      "I5": {
        "rate": 0.8,
        "count": 8,
        "tolerance": {
          "standard": 0.375,
          "display": "3/8",
          "dominance_pct": 100.0,
          "n": 8
        },
        "tier1_enforced": true
      },
      "C3": {
        "rate": 0.9,
        "count": 9,
        "tolerance": {
          "standard": 0.125,
          "display": "1/8",
          "dominance_pct": 100.0,
          "n": 9
        }
      },
      "J9": {
        "rate": 0.8,
        "count": 8,
        "tolerance": {
          "standard": 0.375,
          "display": "3/8",
          "dominance_pct": 100.0,
          "n": 7
        },
        "tier1_enforced": true
      },
      "F10": {
        "rate": 0.5,
        "count": 5,
        "tolerance": {
          "standard": 0.375,
          "display": "3/8",
          "dominance_pct": 100.0,
          "n": 5
        },
        "tier1_enforced": true
      },
      "J10": {
        "rate": 0.6,
        "count": 6,
        "tolerance": {
          "standard": 0.375,
          "display": "3/8",
          "dominance_pct": 100.0,
          "n": 6
        },
        "tier1_enforced": true
      },
      "L8": {
        "rate": 0.5,
        "count": 5,
        "tolerance": {
          "standard": 0.375,
          "display": "3/8",
          "dominance_pct": 100.0,
          "n": 5
        },
        "tier1_enforced": true
      }
    },
    "recommend": {
      "L1": {
        "rate": 0.5,
        "count": 5
      },
      "C6": {
        "rate": 0.6,
        "count": 6,
        "tolerance": {
          "standard": 0.125,
          "display": "1/8",
          "dominance_pct": 100.0,
          "n": 6
        }
      },
      "E9": {
        "rate": 0.5,
        "count": 5,
        "tolerance": {
          "standard": 0.25,
          "display": "1/4",
          "dominance_pct": 100.0,
          "n": 5
        }
      },
      "B34": {
        "rate": 0.6,
        "count": 6,
        "tolerance": {
          "standard": 0.5,
          "display": "1/2",
          "dominance_pct": 100.0,
          "n": 6
        }
      },
      "Z18": {
        "rate": 0.5,
        "count": 5
      },
      "N16": {
        "rate": 0.5,
        "count": 5,
        "tolerance": {
          "standard": 0.125,
          "display": "1/8",
          "dominance_pct": 100.0,
          "n": 5
        }
      }
    },
    "optional": {
      "P5": {
        "rate": 0.4,
        "count": 4,
        "tolerance": {
          "standard": 0.125,
          "display": "1/8",
          "dominance_pct": 100.0,
          "n": 4
        }
      },
      "P7": {
        "rate": 0.4,
        "count": 4,
        "tolerance": {
          "standard": 0.125,
          "display": "1/8",
          "dominance_pct": 100.0,
          "n": 4
        }
      },
      "P54": {
        "rate": 0.4,
        "count": 4,
        "tolerance": {
          "standard": 0.125,
          "display": "1/8",
          "dominance_pct": 100.0,
          "n": 4
        }
      },
      "S7": {
        "rate": 0.4,
        "count": 4
      },
      "S6": {
        "rate": 0.4,
        "count": 4
      },
      "S16": {
        "rate": 0.4,
        "count": 4
      },
      "B5": {
        "rate": 0.4,
        "count": 4,
        "tolerance": {
          "standard": 0.125,
          "display": "1/8",
          "dominance_pct": 100.0,
          "n": 4
        }
      },
      "P50": {
        "rate": 0.4,
        "count": 4,
        "tolerance": {
          "standard": 0.125,
          "display": "1/8",
          "dominance_pct": 100.0,
          "n": 4
        }
      },
      "F6": {
        "rate": 0.4,
        "count": 4,
        "tolerance": {
          "standard": 0.25,
          "display": "1/4",
          "dominance_pct": 100.0,
          "n": 4
        }
      },
      "S18": {
        "rate": 0.3,
        "count": 3,
        "tolerance": {
          "standard": 0.125,
          "display": "1/8",
          "dominance_pct": 100.0,
          "n": 3
        }
      },
      "B7": {
        "rate": 0.4,
        "count": 4,
        "tolerance": {
          "standard": 0.125,
          "display": "1/8",
          "dominance_pct": 100.0,
          "n": 4
        }
      },
      "F9": {
        "rate": 0.4,
        "count": 4,
        "tolerance": {
          "standard": 0.25,
          "display": "1/4",
          "dominance_pct": 100.0,
          "n": 4
        }
      },
      "U5": {
        "rate": 0.3,
        "count": 3,
        "tolerance": {
          "standard": 0.5,
          "display": "1/2",
          "dominance_pct": 100.0,
          "n": 3
        }
      },
      "U1": {
        "rate": 0.3,
        "count": 3,
        "tolerance": {
          "standard": 0.5,
          "display": "1/2",
          "dominance_pct": 100.0,
          "n": 3
        }
      },
      "C7": {
        "rate": 0.3,
        "count": 3,
        "tolerance": {
          "standard": 0.125,
          "display": "1/8",
          "dominance_pct": 100.0,
          "n": 3
        }
      },
      "U12": {
        "rate": 0.3,
        "count": 3,
        "tolerance": {
          "standard": 0.25,
          "display": "1/4",
          "dominance_pct": 100.0,
          "n": 3
        }
      },
      "U7": {
        "rate": 0.3,
        "count": 3,
        "tolerance": {
          "standard": 0.25,
          "display": "1/4",
          "dominance_pct": 100.0,
          "n": 3
        }
      },
      "U6": {
        "rate": 0.3,
        "count": 3,
        "tolerance": {
          "standard": 0.5,
          "display": "1/2",
          "dominance_pct": 100.0,
          "n": 3
        }
      },
      "U11": {
        "rate": 0.3,
        "count": 3
      },
      "L3": {
        "rate": 0.3,
        "count": 3
      },
      "L5": {
        "rate": 0.3,
        "count": 3,
        "tolerance": {
          "standard": 0.375,
          "display": "3/8",
          "dominance_pct": 100.0,
          "n": 3
        }
      },
      "F11": {
        "rate": 0.3,
        "count": 3,
        "tolerance": {
          "standard": 0.375,
          "display": "3/8",
          "dominance_pct": 100.0,
          "n": 3
        }
      },
      "T2": {
        "rate": 0.3,
        "count": 3
      },
      "T10": {
        "rate": 0.3,
        "count": 3
      }
    }
  },
  "median_values": {
    "P5": {
      "size_medians": {
        "2T": 0.333,
        "3T": 0.333,
        "4T": 1.0,
        "5T": 1.0
      }
    },
    "E1": {
      "size_medians": {
        "2T": 0.176,
        "3T": 0.056,
        "4T": 0.263,
        "5T": 0.15
      }
    },
    "N3": {
      "size_medians": {
        "2T": 1.312,
        "3T": 2.688,
        "4T": 0.171,
        "5T": 0.314
      }
    },
    "D13": {
      "size_medians": {
        "2T": 0.6,
        "3T": 1.0,
        "4T": 1.4,
        "5T": 6.0
      }
    },
    "P7": {
      "size_medians": {
        "2T": 3.5,
        "3T": 3.5,
        "4T": 0.333,
        "5T": 0.333
      }
    },
    "P54": {
      "size_medians": {
        "2T": 0.75,
        "3T": 0.75,
        "4T": 3.312,
        "5T": 3.312
      }
    },
    "H1": {
      "size_medians": {
        "2T": 1.0,
        "3T": 1.0,
        "4T": 1.0,
        "5T": 1.0
      }
    },
    "S7": {
      "size_medians": {
        "2T": 0.625,
        "3T": 0.625,
        "4T": 0.625,
        "5T": 0.625
      }
    },
    "S6": {
      "size_medians": {
        "2T": 4.0,
        "3T": 5.0,
        "4T": 5.0,
        "5T": 5.0
      }
    },
    "S16": {
      "size_medians": {
        "2T": 3.0,
        "3T": 3.0,
        "4T": 3.0,
        "5T": 3.0
      }
    },
    "L1": {
      "size_medians": {
        "2T": 0.25,
        "3T": 0.25,
        "4T": 0.25,
        "5T": 0.25
      }
    },
    "B5": {
      "size_medians": {
        "2T": 1.5,
        "3T": 1.5,
        "4T": 1.5,
        "5T": 1.5
      }
    },
    "B25": {
      "size_medians": {
        "2T": 0.4,
        "3T": 0.975,
        "4T": 2.8,
        "5T": 0.2
      }
    },
    "H3": {
      "size_medians": {
        "2T": 0.625,
        "3T": 0.222,
        "4T": 0.556,
        "5T": 5.056
      }
    },
    "K2": {
      "size_medians": {
        "2T": 0.3,
        "3T": 0.3,
        "4T": 9.5,
        "5T": 0.292
      }
    },
    "P50": {
      "size_medians": {
        "2T": 0.75,
        "3T": 0.75,
        "4T": 5.0,
        "5T": 5.0
      }
    },
    "O4": {
      "size_medians": {
        "2T": 0.5,
        "3T": 0.214,
        "4T": 0.312,
        "5T": 0.122
      }
    },
    "E13": {
      "size_medians": {
        "2T": 1.583,
        "3T": 1.0,
        "4T": 1.0,
        "5T": 2.667
      }
    },
    "N9": {
      "size_medians": {
        "2T": 3.5,
        "3T": 2.375,
        "4T": 0.208,
        "5T": 0.339
      }
    },
    "F6": {
      "size_medians": {
        "2T": 0.715,
        "3T": 10.0,
        "4T": 0.428,
        "5T": 5.15
      }
    },
    "S18": {
      "size_medians": {
        "2T": 0.75,
        "3T": 0.75,
        "4T": 0.75,
        "5T": 0.75
      }
    },
    "B26": {
      "size_medians": {
        "2T": 2.188,
        "3T": 2.0,
        "4T": 1.5,
        "5T": 0.5
      }
    },
    "K1": {
      "size_medians": {
        "2T": 0.143,
        "3T": 0.286,
        "4T": 0.143,
        "5T": 0.429
      }
    },
    "B7": {
      "size_medians": {
        "2T": 2.0,
        "3T": 2.0,
        "4T": 2.0,
        "5T": 2.0
      }
    },
    "H4": {
      "size_medians": {
        "2T": 0.125,
        "3T": 0.25,
        "4T": 0.583,
        "5T": 0.077
      }
    },
    "F9": {
      "size_medians": {
        "2T": 0.778,
        "3T": 0.175,
        "4T": 0.5,
        "5T": 11.0
      }
    },
    "C1": {
      "size_medians": {
        "2T": 0.375,
        "3T": 9.0,
        "4T": 0.111,
        "5T": 0.111
      }
    },
    "F10": {
      "size_medians": {
        "2T": 0.583,
        "3T": 0.077,
        "4T": 0.385,
        "5T": 14.0
      }
    },
    "B29": {
      "size_medians": {
        "2T": 1.0,
        "3T": 1.0,
        "4T": 1.0,
        "5T": 1.0
      }
    },
    "I5": {
      "size_medians": {
        "2T": 0.583,
        "3T": 0.077,
        "4T": 0.385,
        "5T": 7.25
      }
    },
    "J10": {
      "size_medians": {
        "2T": 0.467,
        "3T": 0.188,
        "4T": 0.294,
        "5T": 0.196
      }
    },
    "C6": {
      "size_medians": {
        "2T": 0.5,
        "3T": 0.5,
        "4T": 0.5,
        "5T": 0.5
      }
    },
    "L8": {
      "size_medians": {
        "2T": 0.636,
        "3T": 0.231,
        "4T": 0.417,
        "5T": 13.0
      }
    },
    "C3": {
      "size_medians": {
        "2T": 0.75,
        "3T": 0.75,
        "4T": 0.75,
        "5T": 0.75
      }
    },
    "E9": {
      "size_medians": {
        "2T": 0.25,
        "3T": 1.25,
        "4T": 0.75,
        "5T": 1.75
      }
    },
    "U5": {
      "size_medians": {
        "2T": 0.279,
        "3T": 18.0,
        "4T": 0.278,
        "5T": 19.0
      }
    },
    "U14": {
      "size_medians": {
        "2T": 0.375,
        "3T": 10.188,
        "4T": 10.0,
        "5T": 10.562
      }
    },
    "U1": {
      "size_medians": {
        "2T": 20.0,
        "3T": 0.05,
        "4T": 21.0,
        "5T": 0.048
      }
    },
    "J9": {
      "size_medians": {
        "2T": 0.232,
        "3T": 8.1,
        "4T": 0.303,
        "5T": 0.059
      }
    },
    "B34": {
      "size_medians": {
        "2T": 21.5,
        "3T": 21.5,
        "4T": 21.5,
        "5T": 22.5
      }
    },
    "Z18": {
      "size_medians": {
        "2T": 0.625,
        "3T": 0.625,
        "4T": 0.625,
        "5T": 0.625
      }
    },
    "C7": {
      "size_medians": {
        "2T": 0.375,
        "3T": 0.375,
        "4T": 0.375,
        "5T": 0.375
      }
    },
    "U12": {
      "size_medians": {
        "2T": 0.167,
        "3T": 0.5,
        "4T": 0.833,
        "5T": 1.167
      }
    },
    "N16": {
      "size_medians": {
        "2T": 1.312,
        "3T": 0.625,
        "4T": 1.312,
        "5T": 0.625
      }
    },
    "U7": {
      "size_medians": {
        "2T": 0.333,
        "3T": 10.0,
        "4T": 0.25,
        "5T": 0.111
      }
    },
    "U4": {
      "size_medians": {
        "2T": 0.105,
        "3T": 10.025,
        "4T": 0.1,
        "5T": 10.524
      }
    },
    "U6": {
      "size_medians": {
        "2T": 20.0,
        "3T": 0.053,
        "4T": 21.0,
        "5T": 0.053
      }
    },
    "U11": {
      "size_medians": {
        "2T": 3.5,
        "3T": 0.333,
        "4T": 0.333,
        "5T": 1.0
      }
    },
    "N13": {
      "size_medians": {
        "2T": 3.562,
        "3T": 0.259,
        "4T": 0.321,
        "5T": 0.589
      }
    },
    "L3": {
      "size_medians": {
        "2T": 5.0,
        "3T": 5.0,
        "4T": 5.0,
        "5T": 0.2
      }
    },
    "L5": {
      "size_medians": {
        "2T": 0.25,
        "3T": 0.25,
        "4T": 0.077,
        "5T": 0.077
      }
    },
    "U8": {
      "size_medians": {
        "3T": 4.688,
        "5T": 4.812
      }
    },
    "F11": {
      "size_medians": {
        "2T": 0.583,
        "3T": 0.077,
        "4T": 0.385,
        "5T": 14.0
      }
    },
    "B35": {
      "size_medians": {
        "2T": 0.875,
        "3T": 0.875,
        "4T": 0.875,
        "5T": 0.875
      }
    },
    "P6": {
      "size_medians": {
        "2T": 1.5,
        "3T": 1.5,
        "4T": 3.0,
        "5T": 3.0
      }
    },
    "T2": {
      "size_medians": {
        "2T": 0.75,
        "3T": 0.75,
        "4T": 0.75,
        "5T": 0.75
      }
    },
    "T10": {
      "size_medians": {
        "2T": 0.5,
        "3T": 0.5,
        "4T": 0.5,
        "5T": 0.5
      }
    },
    "S2": {
      "size_medians": {
        "2T": 2.25,
        "3T": 2.25,
        "4T": 2.25,
        "5T": 2.25
      }
    },
    "S1": {
      "size_medians": {
        "2T": 1.0,
        "3T": 1.0,
        "4T": 1.0,
        "5T": 1.0
      }
    }
  },
  "grading_rules": {
    "P5": {
      "typical_increment": 0.0,
      "n_pairs": 12
    },
    "E1": {
      "typical_increment": -0.003,
      "n_pairs": 18
    },
    "N3": {
      "typical_increment": 0.111,
      "n_pairs": 24
    },
    "D13": {
      "typical_increment": 0.4,
      "n_pairs": 27
    },
    "P7": {
      "typical_increment": 0.0,
      "n_pairs": 12
    },
    "P54": {
      "typical_increment": 0.0,
      "n_pairs": 12
    },
    "H1": {
      "typical_increment": 0.0,
      "n_pairs": 30
    },
    "S7": {
      "typical_increment": 0.0,
      "n_pairs": 12
    },
    "S6": {
      "typical_increment": 0.0,
      "n_pairs": 12
    },
    "S16": {
      "typical_increment": 0.0,
      "n_pairs": 12
    },
    "L1": {
      "typical_increment": 0.0,
      "n_pairs": 15
    },
    "B5": {
      "typical_increment": 0.0,
      "n_pairs": 12
    },
    "B25": {
      "typical_increment": 0.0,
      "n_pairs": 30
    },
    "H3": {
      "typical_increment": 0.0,
      "n_pairs": 24
    },
    "K2": {
      "typical_increment": 0.0,
      "n_pairs": 20
    },
    "P50": {
      "typical_increment": 0.0,
      "n_pairs": 12
    },
    "O4": {
      "typical_increment": -0.014,
      "n_pairs": 25
    },
    "E13": {
      "typical_increment": 0.0,
      "n_pairs": 24
    },
    "N9": {
      "typical_increment": 0.0,
      "n_pairs": 24
    },
    "F6": {
      "typical_increment": 0.375,
      "n_pairs": 12
    },
    "S18": {
      "typical_increment": 0.0,
      "n_pairs": 9
    },
    "B26": {
      "typical_increment": 0.0,
      "n_pairs": 30
    },
    "K1": {
      "typical_increment": 0.0,
      "n_pairs": 29
    },
    "B7": {
      "typical_increment": 0.0,
      "n_pairs": 12
    },
    "H4": {
      "typical_increment": 0.0,
      "n_pairs": 20
    },
    "F9": {
      "typical_increment": 0.0,
      "n_pairs": 9
    },
    "C1": {
      "typical_increment": 0.0,
      "n_pairs": 24
    },
    "F10": {
      "typical_increment": 0.0,
      "n_pairs": 10
    },
    "B29": {
      "typical_increment": 0.0,
      "n_pairs": 30
    },
    "I5": {
      "typical_increment": 0.0,
      "n_pairs": 19
    },
    "J10": {
      "typical_increment": -0.138,
      "n_pairs": 16
    },
    "C6": {
      "typical_increment": 0.0,
      "n_pairs": 18
    },
    "L8": {
      "typical_increment": 0.0,
      "n_pairs": 9
    },
    "C3": {
      "typical_increment": 0.0,
      "n_pairs": 27
    },
    "E9": {
      "typical_increment": 0.125,
      "n_pairs": 15
    },
    "U14": {
      "typical_increment": 0.125,
      "n_pairs": 5
    },
    "U1": {
      "typical_increment": 0.5,
      "n_pairs": 2
    },
    "J9": {
      "typical_increment": -0.148,
      "n_pairs": 15
    },
    "B34": {
      "typical_increment": 0.0,
      "n_pairs": 18
    },
    "Z18": {
      "typical_increment": 0.0,
      "n_pairs": 15
    },
    "C7": {
      "typical_increment": 0.0,
      "n_pairs": 9
    },
    "U12": {
      "typical_increment": 0.333,
      "n_pairs": 9
    },
    "N16": {
      "typical_increment": 0.0,
      "n_pairs": 15
    },
    "U7": {
      "typical_increment": 0.0,
      "n_pairs": 9
    },
    "U9": {
      "typical_increment": 0.4,
      "n_pairs": 3
    },
    "U4": {
      "typical_increment": -0.102,
      "n_pairs": 3
    },
    "U6": {
      "typical_increment": 0.053,
      "n_pairs": 5
    },
    "U11": {
      "typical_increment": 0.0,
      "n_pairs": 9
    },
    "N13": {
      "typical_increment": 0.188,
      "n_pairs": 6
    },
    "L3": {
      "typical_increment": 0.0,
      "n_pairs": 9
    },
    "L5": {
      "typical_increment": 0.0,
      "n_pairs": 9
    },
    "E2": {
      "typical_increment": 0.5,
      "n_pairs": 3
    },
    "U8": {
      "typical_increment": 0.25,
      "n_pairs": 4
    },
    "F11": {
      "typical_increment": 0.0,
      "n_pairs": 7
    },
    "U13": {
      "typical_increment": 0.333,
      "n_pairs": 3
    },
    "B35": {
      "typical_increment": 0.0,
      "n_pairs": 6
    },
    "B9": {
      "typical_increment": 0.0,
      "n_pairs": 6
    },
    "P6": {
      "typical_increment": 0.0,
      "n_pairs": 6
    },
    "T2": {
      "typical_increment": 0.0,
      "n_pairs": 9
    },
    "E3": {
      "typical_increment": 0.25,
      "n_pairs": 3
    },
    "T10": {
      "typical_increment": 0.0,
      "n_pairs": 9
    },
    "S2": {
      "typical_increment": 0.0,
      "n_pairs": 6
    },
    "D21": {
      "typical_increment": 0.0,
      "n_pairs": 3
    },
    "E6": {
      "typical_increment": -9.9,
      "n_pairs": 1
    },
    "C4": {
      "typical_increment": 0.0,
      "n_pairs": 3
    },
    "D19": {
      "typical_increment": 0.0,
      "n_pairs": 3
    },
    "S1": {
      "typical_increment": 0.0,
      "n_pairs": 6
    },
    "D20": {
      "typical_increment": 0.0,
      "n_pairs": 3
    }
  },
  "tolerance_standards": {
    "P5": {
      "standard": 0.125,
      "display": "1/8",
      "dominance_pct": 100.0,
      "n": 4
    },
    "E1": {
      "standard": 0.375,
      "display": "3/8",
      "dominance_pct": 100.0,
      "n": 7
    },
    "N3": {
      "standard": 0.25,
      "display": "1/4",
      "dominance_pct": 100.0,
      "n": 8
    },
    "D13": {
      "standard": 0.25,
      "display": "1/4",
      "dominance_pct": 100.0,
      "n": 9
    },
    "P7": {
      "standard": 0.125,
      "display": "1/8",
      "dominance_pct": 100.0,
      "n": 4
    },
    "P54": {
      "standard": 0.125,
      "display": "1/8",
      "dominance_pct": 100.0,
      "n": 4
    },
    "B5": {
      "standard": 0.125,
      "display": "1/8",
      "dominance_pct": 100.0,
      "n": 4
    },
    "B25": {
      "standard": 0.25,
      "display": "1/4",
      "dominance_pct": 100.0,
      "n": 10
    },
    "H3": {
      "standard": 0.375,
      "display": "3/8",
      "dominance_pct": 100.0,
      "n": 8
    },
    "K2": {
      "standard": 0.25,
      "display": "1/4",
      "dominance_pct": 100.0,
      "n": 10
    },
    "P50": {
      "standard": 0.125,
      "display": "1/8",
      "dominance_pct": 100.0,
      "n": 4
    },
    "O4": {
      "standard": 0.5,
      "display": "1/2",
      "dominance_pct": 80.0,
      "n": 10
    },
    "E13": {
      "standard": 0.125,
      "display": "1/8",
      "dominance_pct": 87.5,
      "n": 8
    },
    "N9": {
      "standard": 0.25,
      "display": "1/4",
      "dominance_pct": 100.0,
      "n": 8
    },
    "F6": {
      "standard": 0.25,
      "display": "1/4",
      "dominance_pct": 100.0,
      "n": 4
    },
    "S18": {
      "standard": 0.125,
      "display": "1/8",
      "dominance_pct": 100.0,
      "n": 3
    },
    "B26": {
      "standard": 0.125,
      "display": "1/8",
      "dominance_pct": 100.0,
      "n": 10
    },
    "K1": {
      "standard": 0.25,
      "display": "1/4",
      "dominance_pct": 100.0,
      "n": 10
    },
    "B7": {
      "standard": 0.125,
      "display": "1/8",
      "dominance_pct": 100.0,
      "n": 4
    },
    "H4": {
      "standard": 0.375,
      "display": "3/8",
      "dominance_pct": 100.0,
      "n": 10
    },
    "F9": {
      "standard": 0.25,
      "display": "1/4",
      "dominance_pct": 100.0,
      "n": 4
    },
    "C1": {
      "standard": 0.25,
      "display": "1/4",
      "dominance_pct": 100.0,
      "n": 9
    },
    "F10": {
      "standard": 0.375,
      "display": "3/8",
      "dominance_pct": 100.0,
      "n": 5
    },
    "B29": {
      "standard": 0.125,
      "display": "1/8",
      "dominance_pct": 100.0,
      "n": 10
    },
    "I5": {
      "standard": 0.375,
      "display": "3/8",
      "dominance_pct": 100.0,
      "n": 8
    },
    "J10": {
      "standard": 0.375,
      "display": "3/8",
      "dominance_pct": 100.0,
      "n": 6
    },
    "C6": {
      "standard": 0.125,
      "display": "1/8",
      "dominance_pct": 100.0,
      "n": 6
    },
    "L8": {
      "standard": 0.375,
      "display": "3/8",
      "dominance_pct": 100.0,
      "n": 5
    },
    "C3": {
      "standard": 0.125,
      "display": "1/8",
      "dominance_pct": 100.0,
      "n": 9
    },
    "E9": {
      "standard": 0.25,
      "display": "1/4",
      "dominance_pct": 100.0,
      "n": 5
    },
    "U5": {
      "standard": 0.5,
      "display": "1/2",
      "dominance_pct": 100.0,
      "n": 3
    },
    "U14": {
      "standard": 0.25,
      "display": "1/4",
      "dominance_pct": 100.0,
      "n": 2
    },
    "U1": {
      "standard": 0.5,
      "display": "1/2",
      "dominance_pct": 100.0,
      "n": 3
    },
    "J9": {
      "standard": 0.375,
      "display": "3/8",
      "dominance_pct": 100.0,
      "n": 7
    },
    "B34": {
      "standard": 0.5,
      "display": "1/2",
      "dominance_pct": 100.0,
      "n": 6
    },
    "C7": {
      "standard": 0.125,
      "display": "1/8",
      "dominance_pct": 100.0,
      "n": 3
    },
    "U12": {
      "standard": 0.25,
      "display": "1/4",
      "dominance_pct": 100.0,
      "n": 3
    },
    "N16": {
      "standard": 0.125,
      "display": "1/8",
      "dominance_pct": 100.0,
      "n": 5
    },
    "U7": {
      "standard": 0.25,
      "display": "1/4",
      "dominance_pct": 100.0,
      "n": 3
    },
    "U9": {
      "standard": 0.25,
      "display": "1/4",
      "dominance_pct": 100.0,
      "n": 1
    },
    "U4": {
      "standard": 0.5,
      "display": "1/2",
      "dominance_pct": 100.0,
      "n": 2
    },
    "U6": {
      "standard": 0.5,
      "display": "1/2",
      "dominance_pct": 100.0,
      "n": 3
    },
    "N13": {
      "standard": 0.25,
      "display": "1/4",
      "dominance_pct": 100.0,
      "n": 2
    },
    "L5": {
      "standard": 0.375,
      "display": "3/8",
      "dominance_pct": 100.0,
      "n": 3
    },
    "E2": {
      "standard": 0.25,
      "display": "1/4",
      "dominance_pct": 100.0,
      "n": 1
    },
    "U8": {
      "standard": 0.25,
      "display": "1/4",
      "dominance_pct": 100.0,
      "n": 2
    },
    "F11": {
      "standard": 0.375,
      "display": "3/8",
      "dominance_pct": 100.0,
      "n": 3
    },
    "U13": {
      "standard": 0.25,
      "display": "1/4",
      "dominance_pct": 100.0,
      "n": 1
    },
    "B9": {
      "standard": 0.125,
      "display": "1/8",
      "dominance_pct": 100.0,
      "n": 2
    },
    "P6": {
      "standard": 0.125,
      "display": "1/8",
      "dominance_pct": 100.0,
      "n": 2
    },
    "E3": {
      "standard": 0.125,
      "display": "1/8",
      "dominance_pct": 100.0,
      "n": 1
    },
    "S2": {
      "standard": 0.125,
      "display": "1/8",
      "dominance_pct": 100.0,
      "n": 2
    },
    "D21": {
      "standard": 0.125,
      "display": "1/8",
      "dominance_pct": 100.0,
      "n": 1
    },
    "C4": {
      "standard": 0.125,
      "display": "1/8",
      "dominance_pct": 100.0,
      "n": 1
    },
    "D19": {
      "standard": 0.25,
      "display": "1/4",
      "dominance_pct": 100.0,
      "n": 1
    },
    "S1": {
      "standard": 0.125,
      "display": "1/8",
      "dominance_pct": 100.0,
      "n": 2
    },
    "D20": {
      "standard": 0.125,
      "display": "1/8",
      "dominance_pct": 100.0,
      "n": 1
    }
  },
  "pom_sort_order": [
    "H3",
    "B25",
    "B26",
    "B29",
    "H4",
    "H1",
    "L5",
    "B5",
    "L3",
    "B7",
    "F6",
    "F9",
    "F10",
    "L1",
    "K1",
    "L8",
    "I5",
    "C7",
    "K2",
    "N13",
    "C1",
    "C3",
    "N3",
    "C6",
    "E1",
    "B35",
    "D13",
    "B34",
    "Z18",
    "E9",
    "N16",
    "E13",
    "N9",
    "J10",
    "T2",
    "S18",
    "T10",
    "O4",
    "P5",
    "P7",
    "S7",
    "S16",
    "S6",
    "J9",
    "P50",
    "S1",
    "U1",
    "U14",
    "U7",
    "S2",
    "F11",
    "P6",
    "U4",
    "U12",
    "U6",
    "U11",
    "U5",
    "U8",
    "P54"
  ],
  "foundational_measurements": {
    "codes": [
      "F10",
      "C1",
      "J9",
      "H1",
      "K1",
      "L2",
      "N9",
      "O4"
    ],
    "present": [
      "F10",
      "C1",
      "J9",
      "H1",
      "K1",
      "N9",
      "O4"
    ],
    "missing": [
      "L2"
    ],
    "coverage": 0.875,
    "description": "Core measurements that define garment fit. Higher coverage = more reliable rules."
  }
}