{
  "version": "v1.0",
  "created": "2026-04-20",
  "garment_type": "PANT",
  "item_type": "PANTS",
  "gt_it_key": "PANT|PANTS",
  "n_designs": 80,
  "n_with_iso": 38,
  "data_source": "ONY 2026 6 seasons, expanded_bridge_v6",
  "usage": "Techpack Creation UI: 選定 GT×IT 後，自動帶入做工配方",
  "tier_rules": {
    "required": "≥80% 設計都有此部位 → UI 預設展開",
    "recommended": "50-79% → UI 推薦勾選",
    "optional": "25-49% → UI 列出但不預選",
    "rare": "<25% → UI 隱藏，進階模式才看到"
  },
  "iso_confidence_rules": {
    "high": "Top ISO ≥60% & N≥5 → 自動選定（綠色）",
    "medium": "Top ISO ≥40% & N≥5 → 推薦（黃色）",
    "low": "Top ISO <40% 或 N<5 → 手動選（灰色）"
  },
  "zones": [
    {
      "l1_zh": "大身",
      "l1_code": "BD",
      "tier": "required",
      "presence_rate": 98.8,
      "presence_count": 79,
      "iso_breakdown": [
        {
          "iso": "406",
          "iso_name_en": "Coverstitch",
          "iso_name_zh": "三本雙針/壓三本",
          "pct": 28.4,
          "count": 114,
          "confidence": "low"
        },
        {
          "iso": "605",
          "iso_name_en": "Flatseam Binding",
          "iso_name_zh": "三針五線爬網",
          "pct": 24.7,
          "count": 99,
          "confidence": "low"
        },
        {
          "iso": "514",
          "iso_name_en": "4-thread Overlock",
          "iso_name_zh": "四線拷克",
          "pct": 23.4,
          "count": 94,
          "confidence": "low"
        },
        {
          "iso": "607",
          "iso_name_en": "Flatlock",
          "iso_name_zh": "併逢車",
          "pct": 9.7,
          "count": 39,
          "confidence": "low"
        },
        {
          "iso": "401",
          "iso_name_en": "Chainstitch",
          "iso_name_zh": "鎖鍊",
          "pct": 9.2,
          "count": 37,
          "confidence": "low"
        },
        {
          "iso": "602",
          "iso_name_en": "Flatseam 2-needle",
          "iso_name_zh": "併縫",
          "pct": 3.2,
          "count": 13,
          "confidence": "low"
        },
        {
          "iso": "301",
          "iso_name_en": "Lockstitch",
          "iso_name_zh": "平車",
          "pct": 1.2,
          "count": 5,
          "confidence": "low"
        }
      ]
    },
    {
      "l1_zh": "腰頭",
      "l1_code": "WB",
      "tier": "required",
      "presence_rate": 97.5,
      "presence_count": 78,
      "iso_breakdown": [
        {
          "iso": "406",
          "iso_name_en": "Coverstitch",
          "iso_name_zh": "三本雙針/壓三本",
          "pct": 29.1,
          "count": 99,
          "confidence": "low"
        },
        {
          "iso": "605",
          "iso_name_en": "Flatseam Binding",
          "iso_name_zh": "三針五線爬網",
          "pct": 25.9,
          "count": 88,
          "confidence": "low"
        },
        {
          "iso": "514",
          "iso_name_en": "4-thread Overlock",
          "iso_name_zh": "四線拷克",
          "pct": 22.9,
          "count": 78,
          "confidence": "low"
        },
        {
          "iso": "607",
          "iso_name_en": "Flatlock",
          "iso_name_zh": "併逢車",
          "pct": 8.2,
          "count": 28,
          "confidence": "low"
        },
        {
          "iso": "401",
          "iso_name_en": "Chainstitch",
          "iso_name_zh": "鎖鍊",
          "pct": 7.9,
          "count": 27,
          "confidence": "low"
        },
        {
          "iso": "602",
          "iso_name_en": "Flatseam 2-needle",
          "iso_name_zh": "併縫",
          "pct": 3.8,
          "count": 13,
          "confidence": "low"
        },
        {
          "iso": "301",
          "iso_name_en": "Lockstitch",
          "iso_name_zh": "平車",
          "pct": 2.1,
          "count": 7,
          "confidence": "low"
        }
      ]
    },
    {
      "l1_zh": "褲口",
      "l1_code": "LO",
      "tier": "required",
      "presence_rate": 90.0,
      "presence_count": 72,
      "iso_breakdown": [
        {
          "iso": "406",
          "iso_name_en": "Coverstitch",
          "iso_name_zh": "三本雙針/壓三本",
          "pct": 26.8,
          "count": 91,
          "confidence": "low"
        },
        {
          "iso": "605",
          "iso_name_en": "Flatseam Binding",
          "iso_name_zh": "三針五線爬網",
          "pct": 25.6,
          "count": 87,
          "confidence": "low"
        },
        {
          "iso": "514",
          "iso_name_en": "4-thread Overlock",
          "iso_name_zh": "四線拷克",
          "pct": 24.4,
          "count": 83,
          "confidence": "low"
        },
        {
          "iso": "401",
          "iso_name_en": "Chainstitch",
          "iso_name_zh": "鎖鍊",
          "pct": 9.4,
          "count": 32,
          "confidence": "low"
        },
        {
          "iso": "607",
          "iso_name_en": "Flatlock",
          "iso_name_zh": "併逢車",
          "pct": 8.2,
          "count": 28,
          "confidence": "low"
        },
        {
          "iso": "602",
          "iso_name_en": "Flatseam 2-needle",
          "iso_name_zh": "併縫",
          "pct": 3.8,
          "count": 13,
          "confidence": "low"
        },
        {
          "iso": "301",
          "iso_name_en": "Lockstitch",
          "iso_name_zh": "平車",
          "pct": 1.8,
          "count": 6,
          "confidence": "low"
        }
      ]
    },
    {
      "l1_zh": "褲合身",
      "l1_code": "PS",
      "tier": "required",
      "presence_rate": 87.5,
      "presence_count": 70,
      "iso_breakdown": [
        {
          "iso": "406",
          "iso_name_en": "Coverstitch",
          "iso_name_zh": "三本雙針/壓三本",
          "pct": 52.6,
          "count": 10,
          "confidence": "medium"
        },
        {
          "iso": "605",
          "iso_name_en": "Flatseam Binding",
          "iso_name_zh": "三針五線爬網",
          "pct": 21.1,
          "count": 4,
          "confidence": "low"
        },
        {
          "iso": "514",
          "iso_name_en": "4-thread Overlock",
          "iso_name_zh": "四線拷克",
          "pct": 15.8,
          "count": 3,
          "confidence": "low"
        },
        {
          "iso": "607",
          "iso_name_en": "Flatlock",
          "iso_name_zh": "併逢車",
          "pct": 10.5,
          "count": 2,
          "confidence": "low"
        }
      ]
    },
    {
      "l1_zh": "口袋",
      "l1_code": "PK",
      "tier": "required",
      "presence_rate": 86.2,
      "presence_count": 69,
      "iso_breakdown": [
        {
          "iso": "605",
          "iso_name_en": "Flatseam Binding",
          "iso_name_zh": "三針五線爬網",
          "pct": 29.1,
          "count": 96,
          "confidence": "low"
        },
        {
          "iso": "406",
          "iso_name_en": "Coverstitch",
          "iso_name_zh": "三本雙針/壓三本",
          "pct": 27.0,
          "count": 89,
          "confidence": "low"
        },
        {
          "iso": "514",
          "iso_name_en": "4-thread Overlock",
          "iso_name_zh": "四線拷克",
          "pct": 23.3,
          "count": 77,
          "confidence": "low"
        },
        {
          "iso": "401",
          "iso_name_en": "Chainstitch",
          "iso_name_zh": "鎖鍊",
          "pct": 7.6,
          "count": 25,
          "confidence": "low"
        },
        {
          "iso": "607",
          "iso_name_en": "Flatlock",
          "iso_name_zh": "併逢車",
          "pct": 5.5,
          "count": 18,
          "confidence": "low"
        },
        {
          "iso": "602",
          "iso_name_en": "Flatseam 2-needle",
          "iso_name_zh": "併縫",
          "pct": 5.2,
          "count": 17,
          "confidence": "low"
        },
        {
          "iso": "301",
          "iso_name_en": "Lockstitch",
          "iso_name_zh": "平車",
          "pct": 2.4,
          "count": 8,
          "confidence": "low"
        }
      ]
    },
    {
      "l1_zh": "標",
      "l1_code": "LB",
      "tier": "required",
      "presence_rate": 81.2,
      "presence_count": 65,
      "iso_breakdown": [
        {
          "iso": "406",
          "iso_name_en": "Coverstitch",
          "iso_name_zh": "三本雙針/壓三本",
          "pct": 70.0,
          "count": 7,
          "confidence": "high"
        },
        {
          "iso": "514",
          "iso_name_en": "4-thread Overlock",
          "iso_name_zh": "四線拷克",
          "pct": 30.0,
          "count": 3,
          "confidence": "low"
        }
      ]
    },
    {
      "l1_zh": "後褲身",
      "l1_code": "BR",
      "tier": "recommended",
      "presence_rate": 72.5,
      "presence_count": 58,
      "iso_breakdown": [
        {
          "iso": "406",
          "iso_name_en": "Coverstitch",
          "iso_name_zh": "三本雙針/壓三本",
          "pct": 66.7,
          "count": 4,
          "confidence": "high"
        },
        {
          "iso": "514",
          "iso_name_en": "4-thread Overlock",
          "iso_name_zh": "四線拷克",
          "pct": 16.7,
          "count": 1,
          "confidence": "low"
        },
        {
          "iso": "605",
          "iso_name_en": "Flatseam Binding",
          "iso_name_zh": "三針五線爬網",
          "pct": 16.7,
          "count": 1,
          "confidence": "low"
        }
      ]
    },
    {
      "l1_zh": "前褲身",
      "l1_code": "FR",
      "tier": "recommended",
      "presence_rate": 71.2,
      "presence_count": 57,
      "iso_breakdown": [
        {
          "iso": "406",
          "iso_name_en": "Coverstitch",
          "iso_name_zh": "三本雙針/壓三本",
          "pct": 75.0,
          "count": 3,
          "confidence": "low"
        },
        {
          "iso": "514",
          "iso_name_en": "4-thread Overlock",
          "iso_name_zh": "四線拷克",
          "pct": 25.0,
          "count": 1,
          "confidence": "low"
        }
      ]
    },
    {
      "l1_zh": "袖",
      "l1_code": "SL",
      "tier": "recommended",
      "presence_rate": 66.2,
      "presence_count": 53,
      "iso_breakdown": [
        {
          "iso": "514",
          "iso_name_en": "4-thread Overlock",
          "iso_name_zh": "四線拷克",
          "pct": 63.6,
          "count": 14,
          "confidence": "high"
        },
        {
          "iso": "401",
          "iso_name_en": "Chainstitch",
          "iso_name_zh": "鎖鍊",
          "pct": 22.7,
          "count": 5,
          "confidence": "low"
        },
        {
          "iso": "406",
          "iso_name_en": "Coverstitch",
          "iso_name_zh": "三本雙針/壓三本",
          "pct": 13.6,
          "count": 3,
          "confidence": "low"
        }
      ]
    },
    {
      "l1_zh": "前立",
      "l1_code": "FP",
      "tier": "recommended",
      "presence_rate": 65.0,
      "presence_count": 52,
      "iso_breakdown": [
        {
          "iso": "406",
          "iso_name_en": "Coverstitch",
          "iso_name_zh": "三本雙針/壓三本",
          "pct": 34.0,
          "count": 65,
          "confidence": "low"
        },
        {
          "iso": "605",
          "iso_name_en": "Flatseam Binding",
          "iso_name_zh": "三針五線爬網",
          "pct": 22.5,
          "count": 43,
          "confidence": "low"
        },
        {
          "iso": "514",
          "iso_name_en": "4-thread Overlock",
          "iso_name_zh": "四線拷克",
          "pct": 20.9,
          "count": 40,
          "confidence": "low"
        },
        {
          "iso": "607",
          "iso_name_en": "Flatlock",
          "iso_name_zh": "併逢車",
          "pct": 9.9,
          "count": 19,
          "confidence": "low"
        },
        {
          "iso": "401",
          "iso_name_en": "Chainstitch",
          "iso_name_zh": "鎖鍊",
          "pct": 5.8,
          "count": 11,
          "confidence": "low"
        },
        {
          "iso": "602",
          "iso_name_en": "Flatseam 2-needle",
          "iso_name_zh": "併縫",
          "pct": 5.2,
          "count": 10,
          "confidence": "low"
        },
        {
          "iso": "301",
          "iso_name_en": "Lockstitch",
          "iso_name_zh": "平車",
          "pct": 1.6,
          "count": 3,
          "confidence": "low"
        }
      ]
    },
    {
      "l1_zh": "下擺",
      "l1_code": "HM",
      "tier": "recommended",
      "presence_rate": 63.7,
      "presence_count": 51,
      "iso_breakdown": [
        {
          "iso": "605",
          "iso_name_en": "Flatseam Binding",
          "iso_name_zh": "三針五線爬網",
          "pct": 28.5,
          "count": 43,
          "confidence": "low"
        },
        {
          "iso": "406",
          "iso_name_en": "Coverstitch",
          "iso_name_zh": "三本雙針/壓三本",
          "pct": 25.8,
          "count": 39,
          "confidence": "low"
        },
        {
          "iso": "514",
          "iso_name_en": "4-thread Overlock",
          "iso_name_zh": "四線拷克",
          "pct": 16.6,
          "count": 25,
          "confidence": "low"
        },
        {
          "iso": "607",
          "iso_name_en": "Flatlock",
          "iso_name_zh": "併逢車",
          "pct": 11.9,
          "count": 18,
          "confidence": "low"
        },
        {
          "iso": "602",
          "iso_name_en": "Flatseam 2-needle",
          "iso_name_zh": "併縫",
          "pct": 8.6,
          "count": 13,
          "confidence": "low"
        },
        {
          "iso": "401",
          "iso_name_en": "Chainstitch",
          "iso_name_zh": "鎖鍊",
          "pct": 5.3,
          "count": 8,
          "confidence": "low"
        },
        {
          "iso": "301",
          "iso_name_en": "Lockstitch",
          "iso_name_zh": "平車",
          "pct": 3.3,
          "count": 5,
          "confidence": "low"
        }
      ]
    },
    {
      "l1_zh": "鬆緊帶",
      "l1_code": "EL",
      "tier": "recommended",
      "presence_rate": 53.8,
      "presence_count": 43,
      "iso_breakdown": [
        {
          "iso": "514",
          "iso_name_en": "4-thread Overlock",
          "iso_name_zh": "四線拷克",
          "pct": 35.0,
          "count": 36,
          "confidence": "low"
        },
        {
          "iso": "406",
          "iso_name_en": "Coverstitch",
          "iso_name_zh": "三本雙針/壓三本",
          "pct": 34.0,
          "count": 35,
          "confidence": "low"
        },
        {
          "iso": "401",
          "iso_name_en": "Chainstitch",
          "iso_name_zh": "鎖鍊",
          "pct": 15.5,
          "count": 16,
          "confidence": "low"
        },
        {
          "iso": "607",
          "iso_name_en": "Flatlock",
          "iso_name_zh": "併逢車",
          "pct": 7.8,
          "count": 8,
          "confidence": "low"
        },
        {
          "iso": "301",
          "iso_name_en": "Lockstitch",
          "iso_name_zh": "平車",
          "pct": 4.9,
          "count": 5,
          "confidence": "low"
        },
        {
          "iso": "605",
          "iso_name_en": "Flatseam Binding",
          "iso_name_zh": "三針五線爬網",
          "pct": 2.9,
          "count": 3,
          "confidence": "low"
        }
      ]
    },
    {
      "l1_zh": "脇縫",
      "l1_code": "SS",
      "tier": "recommended",
      "presence_rate": 50.0,
      "presence_count": 40,
      "iso_breakdown": [
        {
          "iso": "406",
          "iso_name_en": "Coverstitch",
          "iso_name_zh": "三本雙針/壓三本",
          "pct": 60.0,
          "count": 9,
          "confidence": "high"
        },
        {
          "iso": "514",
          "iso_name_en": "4-thread Overlock",
          "iso_name_zh": "四線拷克",
          "pct": 20.0,
          "count": 3,
          "confidence": "low"
        },
        {
          "iso": "605",
          "iso_name_en": "Flatseam Binding",
          "iso_name_zh": "三針五線爬網",
          "pct": 6.7,
          "count": 1,
          "confidence": "low"
        },
        {
          "iso": "607",
          "iso_name_en": "Flatlock",
          "iso_name_zh": "併逢車",
          "pct": 6.7,
          "count": 1,
          "confidence": "low"
        },
        {
          "iso": "401",
          "iso_name_en": "Chainstitch",
          "iso_name_zh": "鎖鍊",
          "pct": 6.7,
          "count": 1,
          "confidence": "low"
        }
      ]
    },
    {
      "l1_zh": "褲底檔",
      "l1_code": "GS",
      "tier": "optional",
      "presence_rate": 38.8,
      "presence_count": 31,
      "iso_breakdown": []
    },
    {
      "l1_zh": "繩類",
      "l1_code": "DC",
      "tier": "optional",
      "presence_rate": 28.7,
      "presence_count": 23,
      "iso_breakdown": [
        {
          "iso": "406",
          "iso_name_en": "Coverstitch",
          "iso_name_zh": "三本雙針/壓三本",
          "pct": 100.0,
          "count": 6,
          "confidence": "high"
        }
      ]
    },
    {
      "l1_zh": "貼邊",
      "l1_code": "FC",
      "tier": "optional",
      "presence_rate": 26.2,
      "presence_count": 21,
      "iso_breakdown": [
        {
          "iso": "406",
          "iso_name_en": "Coverstitch",
          "iso_name_zh": "三本雙針/壓三本",
          "pct": 100.0,
          "count": 15,
          "confidence": "high"
        }
      ]
    },
    {
      "l1_zh": "褶",
      "l1_code": "PD",
      "tier": "optional",
      "presence_rate": 26.2,
      "presence_count": 21,
      "iso_breakdown": [
        {
          "iso": "406",
          "iso_name_en": "Coverstitch",
          "iso_name_zh": "三本雙針/壓三本",
          "pct": 42.4,
          "count": 14,
          "confidence": "medium"
        },
        {
          "iso": "514",
          "iso_name_en": "4-thread Overlock",
          "iso_name_zh": "四線拷克",
          "pct": 30.3,
          "count": 10,
          "confidence": "low"
        },
        {
          "iso": "605",
          "iso_name_en": "Flatseam Binding",
          "iso_name_zh": "三針五線爬網",
          "pct": 24.2,
          "count": 8,
          "confidence": "low"
        },
        {
          "iso": "301",
          "iso_name_en": "Lockstitch",
          "iso_name_zh": "平車",
          "pct": 3.0,
          "count": 1,
          "confidence": "low"
        }
      ]
    },
    {
      "l1_zh": "拉鍊",
      "l1_code": "ZP",
      "tier": "optional",
      "presence_rate": 25.0,
      "presence_count": 20,
      "iso_breakdown": [
        {
          "iso": "406",
          "iso_name_en": "Coverstitch",
          "iso_name_zh": "三本雙針/壓三本",
          "pct": 100.0,
          "count": 23,
          "confidence": "high"
        }
      ]
    },
    {
      "l1_zh": "鈕扣",
      "l1_code": "BT",
      "tier": "rare",
      "presence_rate": 22.5,
      "presence_count": 18,
      "iso_breakdown": [
        {
          "iso": "406",
          "iso_name_en": "Coverstitch",
          "iso_name_zh": "三本雙針/壓三本",
          "pct": 88.9,
          "count": 8,
          "confidence": "high"
        },
        {
          "iso": "301",
          "iso_name_en": "Lockstitch",
          "iso_name_zh": "平車",
          "pct": 11.1,
          "count": 1,
          "confidence": "low"
        }
      ]
    },
    {
      "l1_zh": "袖口",
      "l1_code": "CF",
      "tier": "rare",
      "presence_rate": 21.2,
      "presence_count": 17,
      "iso_breakdown": [
        {
          "iso": "514",
          "iso_name_en": "4-thread Overlock",
          "iso_name_zh": "四線拷克",
          "pct": 63.2,
          "count": 12,
          "confidence": "high"
        },
        {
          "iso": "401",
          "iso_name_en": "Chainstitch",
          "iso_name_zh": "鎖鍊",
          "pct": 26.3,
          "count": 5,
          "confidence": "low"
        },
        {
          "iso": "406",
          "iso_name_en": "Coverstitch",
          "iso_name_zh": "三本雙針/壓三本",
          "pct": 10.5,
          "count": 2,
          "confidence": "low"
        }
      ]
    },
    {
      "l1_zh": "裡布",
      "l1_code": "LN",
      "tier": "rare",
      "presence_rate": 20.0,
      "presence_count": 16,
      "iso_breakdown": [
        {
          "iso": "406",
          "iso_name_en": "Coverstitch",
          "iso_name_zh": "三本雙針/壓三本",
          "pct": 100.0,
          "count": 4,
          "confidence": "low"
        }
      ]
    },
    {
      "l1_zh": "過肩",
      "l1_code": "YK",
      "tier": "rare",
      "presence_rate": 12.5,
      "presence_count": 10,
      "iso_breakdown": []
    },
    {
      "l1_zh": "褲耳",
      "l1_code": "BL",
      "tier": "rare",
      "presence_rate": 8.8,
      "presence_count": 7,
      "iso_breakdown": [
        {
          "iso": "406",
          "iso_name_en": "Coverstitch",
          "iso_name_zh": "三本雙針/壓三本",
          "pct": 100.0,
          "count": 3,
          "confidence": "low"
        }
      ]
    },
    {
      "l1_zh": "行縫固定棉",
      "l1_code": "IL",
      "tier": "rare",
      "presence_rate": 8.8,
      "presence_count": 7,
      "iso_breakdown": []
    },
    {
      "l1_zh": "貼合",
      "l1_code": "FU",
      "tier": "rare",
      "presence_rate": 3.8,
      "presence_count": 3,
      "iso_breakdown": [
        {
          "iso": "406",
          "iso_name_en": "Coverstitch",
          "iso_name_zh": "三本雙針/壓三本",
          "pct": 50.0,
          "count": 2,
          "confidence": "low"
        },
        {
          "iso": "607",
          "iso_name_en": "Flatlock",
          "iso_name_zh": "併逢車",
          "pct": 50.0,
          "count": 2,
          "confidence": "low"
        }
      ]
    },
    {
      "l1_zh": "帽",
      "l1_code": "HD",
      "tier": "rare",
      "presence_rate": 2.5,
      "presence_count": 2,
      "iso_breakdown": []
    },
    {
      "l1_zh": "門襟",
      "l1_code": "PL",
      "tier": "rare",
      "presence_rate": 2.5,
      "presence_count": 2,
      "iso_breakdown": [
        {
          "iso": "406",
          "iso_name_en": "Coverstitch",
          "iso_name_zh": "三本雙針/壓三本",
          "pct": 100.0,
          "count": 4,
          "confidence": "low"
        }
      ]
    },
    {
      "l1_zh": "肩",
      "l1_code": "SH",
      "tier": "rare",
      "presence_rate": 2.5,
      "presence_count": 2,
      "iso_breakdown": [
        {
          "iso": "605",
          "iso_name_en": "Flatseam Binding",
          "iso_name_zh": "三針五線爬網",
          "pct": 50.0,
          "count": 1,
          "confidence": "low"
        },
        {
          "iso": "406",
          "iso_name_en": "Coverstitch",
          "iso_name_zh": "三本雙針/壓三本",
          "pct": 50.0,
          "count": 1,
          "confidence": "low"
        }
      ]
    },
    {
      "l1_zh": "肩帶",
      "l1_code": "ST",
      "tier": "rare",
      "presence_rate": 1.2,
      "presence_count": 1,
      "iso_breakdown": []
    }
  ],
  "iso_distribution": [
    {
      "iso": "406",
      "iso_name_en": "Coverstitch",
      "iso_name_zh": "三本雙針/壓三本",
      "pct": 27.6,
      "count": 24
    },
    {
      "iso": "514",
      "iso_name_en": "4-thread Overlock",
      "iso_name_zh": "四線拷克",
      "pct": 26.4,
      "count": 23
    },
    {
      "iso": "605",
      "iso_name_en": "Flatseam Binding",
      "iso_name_zh": "三針五線爬網",
      "pct": 21.8,
      "count": 19
    },
    {
      "iso": "607",
      "iso_name_en": "Flatlock",
      "iso_name_zh": "併逢車",
      "pct": 9.2,
      "count": 8
    },
    {
      "iso": "401",
      "iso_name_en": "Chainstitch",
      "iso_name_zh": "鎖鍊",
      "pct": 8.0,
      "count": 7
    },
    {
      "iso": "301",
      "iso_name_en": "Lockstitch",
      "iso_name_zh": "平車",
      "pct": 4.6,
      "count": 4
    },
    {
      "iso": "602",
      "iso_name_en": "Flatseam 2-needle",
      "iso_name_zh": "併縫",
      "pct": 2.3,
      "count": 2
    }
  ],
  "top_zh_methods": [
    {
      "method": "三本雙針(406)",
      "count": 3
    },
    {
      "method": "壓單針平車(301)",
      "count": 2
    },
    {
      "method": "單針平車(301)",
      "count": 1
    },
    {
      "method": "單反摺壓單針平車(301)",
      "count": 1
    }
  ],
  "summary": {
    "required_zones": [
      "大身",
      "腰頭",
      "褲口",
      "褲合身",
      "口袋",
      "標"
    ],
    "recommended_zones": [
      "後褲身",
      "前褲身",
      "袖",
      "前立",
      "下擺",
      "鬆緊帶",
      "脇縫"
    ],
    "optional_zones": [
      "褲底檔",
      "繩類",
      "貼邊",
      "褶",
      "拉鍊"
    ],
    "rare_zones": [
      "鈕扣",
      "袖口",
      "裡布",
      "過肩",
      "褲耳",
      "行縫固定棉",
      "貼合",
      "帽",
      "門襟",
      "肩",
      "肩帶"
    ],
    "dominant_iso": "406",
    "dominant_iso_pct": 27.6
  }
}